pytest_playwright_asyncio/__init__.py
pytest_playwright_asyncio/py.typed
pytest_playwright_asyncio/pytest_playwright.py
pytest_playwright_asyncio-0.7.1.dist-info/LICENSE
pytest_playwright_asyncio-0.7.1.dist-info/METADATA
pytest_playwright_asyncio-0.7.1.dist-info/WHEEL
pytest_playwright_asyncio-0.7.1.dist-info/entry_points.txt
pytest_playwright_asyncio-0.7.1.dist-info/top_level.txt
pytest_playwright_asyncio-0.7.1.dist-info/RECORD
